auditai/__init__.py
auditai/is_newest_version.py
auditai/misc.py
auditai/simulations.py
auditai/stats.py
auditai/version.py
auditai/viz.py
auditai/utils/__init__.py
auditai/utils/cmh.py
auditai/utils/crosstabs.py
auditai/utils/functions.py
auditai/utils/general.py
auditai/utils/validate.py
audit_AI-0.1.1.dist-info/LICENSE.txt
audit_AI-0.1.1.dist-info/METADATA
audit_AI-0.1.1.dist-info/WHEEL
audit_AI-0.1.1.dist-info/top_level.txt
audit_AI-0.1.1.dist-info/RECORD
