Metadata-Version: 2.1
Name: audit-AI
Version: 0.1.1
Summary: audit-AI detects demographic differences in the output of machine learning models or other assessments
Home-page: https://github.com/pymetrics/audit-ai
Author: pymetrics Data Team
Author-email: data@pymetrics.com
License: MIT
Project-URL: Company, https://www.pymetrics.com/science/
Keywords: audit,adverse impact,artificial intelligence,machine learning,fairness,bias,accountability,transparency,discrimination
Platform: UNKNOWN
Classifier: Development Status :: 3 - Alpha
Classifier: License :: OSI Approved :: MIT License
Classifier: Programming Language :: Python :: 2
Classifier: Programming Language :: Python :: 3
Classifier: Intended Audience :: Developers
Classifier: Intended Audience :: Education
Classifier: Intended Audience :: Financial and Insurance Industry
Classifier: Intended Audience :: Healthcare Industry
Classifier: Intended Audience :: Legal Industry
Classifier: Intended Audience :: Other Audience
Classifier: Intended Audience :: Science/Research
Classifier: Natural Language :: English
Classifier: Topic :: Scientific/Engineering
Classifier: Topic :: Scientific/Engineering :: Artificial Intelligence
Classifier: Topic :: Scientific/Engineering :: Visualization
Requires-Dist: numpy
Requires-Dist: scipy
Requires-Dist: pandas
Requires-Dist: matplotlib
Requires-Dist: statsmodels
Requires-Dist: sklearn
Provides-Extra: dev
Requires-Dist: pytest-cov ; extra == 'dev'
Requires-Dist: flake8 ; extra == 'dev'
Requires-Dist: detox ; extra == 'dev'
Requires-Dist: mock ; extra == 'dev'
Requires-Dist: six ; extra == 'dev'
